{
    "data": [{
        "heading": "Introduction",
        "url": "/intro"
    }, {
        "heading": "Trade Service Group",
        "body": [{
                "title": "InfoPrices",
                "url": "/infoPrices"
            },
            {
                "title": "Prices",
                "url": "/prices"
            },
            {
                "title": "Options Chain",
                "url": "/options"
            },
            {
                "title": "Orders",
                "url": "/orders"
            }
        ]
    }, {
        "heading": "Ref Data Service Group",
        "body": [{
            "title": "Instruments",
            "url": "/instruments"
        }]
    }, {
        "heading": "Portfolio Service Group",
        "body": [{
            "title": "Client Portfolio",
            "url": "/clientPortfolio"
        }]
    }, {
        "heading": "Chart",
        "body": [{
            "title": "Chart Polling",
            "url": "/chartPolling"
        }, {
            "title": "Chart Streaming",
            "url": "/chartStreaming"
        }]
    }]
}